examples/__init__.py
examples/example.py
rotplot/__init__.py
rotplot/rotplot.py
rotplot-0.0.1.dist-info/LICENSE
rotplot-0.0.1.dist-info/METADATA
rotplot-0.0.1.dist-info/WHEEL
rotplot-0.0.1.dist-info/top_level.txt
rotplot-0.0.1.dist-info/RECORD
