Metadata-Version: 2.1
Name: rotplot
Version: 0.0.1
Summary: Package to rotate 2D and 3D curves
Home-page: https://github.com/antscloud/rotplot
Author: Ant Gib
Author-email: ant.gib@protonmail.com
License: UNKNOWN
Platform: UNKNOWN
Classifier: Programming Language :: Python :: 3
Classifier: Operating System :: OS Independent
Requires-Python: >=3
Requires-Dist: numpy (>=1)
